zerolan/ui/__init__.py
zerolan/ui/animations/fadeout.py
zerolan/ui/api/toasts.py
zerolan/ui/app.py
zerolan/ui/common/decorators.py
zerolan/ui/common/utils.py
zerolan/ui/subtitle.py
zerolan/ui/themes/modern.py
zerolan/ui/toasts/base_toast.py
zerolan/ui/toasts/progress_toast.py
zerolan/ui/web/entities.py
zerolan_ui-0.1.0.dist-info/METADATA
zerolan_ui-0.1.0.dist-info/WHEEL
zerolan_ui-0.1.0.dist-info/RECORD
