Metadata-Version: 2.1
Name: zerolan-ui
Version: 0.1.0
Summary: 
Author: AkagawaTsurunaki
Author-email: AkagawaTsurunaki@outlook.com
Requires-Python: >=3.10,<4.0
Classifier: Programming Language :: Python :: 3
Classifier: Programming Language :: Python :: 3.10
Classifier: Programming Language :: Python :: 3.11
Classifier: Programming Language :: Python :: 3.12
Classifier: Programming Language :: Python :: 3.13
Requires-Dist: dataclasses-json (>=0.6.7,<0.7.0)
Requires-Dist: flask (>=3.0.3,<4.0.0)
Requires-Dist: loguru (>=0.7.2,<0.8.0)
Requires-Dist: pyqt6 (>=6.7.1,<7.0.0)
Requires-Dist: requests (>=2.32.3,<3.0.0)
